{
  "main": {
    "id": "7854064bdf5674e6",
    "type": "split",
    "children": [
      {
        "id": "f44d7dcc8f55dbfa",
        "type": "tabs",
        "children": [
          {
            "id": "c6440873f26555a2",
            "type": "leaf",
            "state": {
              "type": "markdown",
              "state": {
                "file": "2.fronts/2-css/1.códigos/8.animations/1.transitions/5.transition.md",
                "mode": "source",
                "source": false
              },
              "icon": "lucide-file",
              "title": "5.transition"
            }
          }
        ]
      }
    ],
    "direction": "vertical"
  },
  "left": {
    "id": "e856e3527a248a99",
    "type": "split",
    "children": [
      {
        "id": "a25eba73bedc3878",
        "type": "tabs",
        "children": [
          {
            "id": "9d68e31116c8b7b7",
            "type": "leaf",
            "state": {
              "type": "file-explorer",
              "state": {
                "sortOrder": "alphabetical",
                "autoReveal": false
              },
              "icon": "lucide-folder-closed",
              "title": "Explorador de arquivos"
            }
          },
          {
            "id": "f5ce01623cb93fd6",
            "type": "leaf",
            "state": {
              "type": "search",
              "state": {
                "query": "",
                "matchingCase": false,
                "explainSearch": false,
                "collapseAll": false,
                "extraContext": false,
                "sortOrder": "alphabetical"
              },
              "icon": "lucide-search",
              "title": "Procurar"
            }
          },
          {
            "id": "65155f71804f256c",
            "type": "leaf",
            "state": {
              "type": "bookmarks",
              "state": {},
              "icon": "lucide-bookmark",
              "title": "Marcadores"
            }
          }
        ]
      }
    ],
    "direction": "horizontal",
    "width": 300
  },
  "right": {
    "id": "6fbf90d264e3f64b",
    "type": "split",
    "children": [
      {
        "id": "514c748c263c1f32",
        "type": "tabs",
        "children": [
          {
            "id": "d9517f1f57b6c843",
            "type": "leaf",
            "state": {
              "type": "backlink",
              "state": {
                "file": "1.Math/6.regra de 3 - função linear/O que é regra de 3.md",
                "collapseAll": false,
                "extraContext": false,
                "sortOrder": "alphabetical",
                "showSearch": false,
                "searchQuery": "",
                "backlinkCollapsed": false,
                "unlinkedCollapsed": true
              },
              "icon": "links-coming-in",
              "title": "Links inversos para O que é regra de 3"
            }
          },
          {
            "id": "dca13d0b6c38a81e",
            "type": "leaf",
            "state": {
              "type": "outgoing-link",
              "state": {
                "file": "1.Math/6.regra de 3 - função linear/O que é regra de 3.md",
                "linksCollapsed": false,
                "unlinkedCollapsed": true
              },
              "icon": "links-going-out",
              "title": "Links de saída para O que é regra de 3"
            }
          },
          {
            "id": "ca3127237558b82f",
            "type": "leaf",
            "state": {
              "type": "tag",
              "state": {
                "sortOrder": "frequency",
                "useHierarchy": true,
                "showSearch": false,
                "searchQuery": ""
              },
              "icon": "lucide-tags",
              "title": "Tags"
            }
          },
          {
            "id": "5150cda6d1e6ac65",
            "type": "leaf",
            "state": {
              "type": "all-properties",
              "state": {
                "sortOrder": "frequency",
                "showSearch": false,
                "searchQuery": ""
              },
              "icon": "lucide-archive",
              "title": "Todas as propriedades"
            }
          },
          {
            "id": "940b522324db8784",
            "type": "leaf",
            "state": {
              "type": "outline",
              "state": {
                "file": "1.Math/6.regra de 3 - função linear/O que é regra de 3.md",
                "followCursor": false,
                "showSearch": false,
                "searchQuery": ""
              },
              "icon": "lucide-list",
              "title": "Sumário de O que é regra de 3"
            }
          }
        ]
      }
    ],
    "direction": "horizontal",
    "width": 300,
    "collapsed": true
  },
  "left-ribbon": {
    "hiddenItems": {
      "switcher:Abrir a troca rápida": false,
      "graph:Abrir visualização em gráfico": false,
      "canvas:Criar novo canvas": false,
      "daily-notes:Abrir a nota de hoje": false,
      "templates:Inserir modelo": false,
      "command-palette:Abrir paleta de comandos": false,
      "bases:Criar nova base": false
    }
  },
  "active": "c6440873f26555a2",
  "lastOpenFiles": [
    "2.fronts/2-css/1.códigos/8.animations/1.transitions/4.transition-delay.md",
    "2.fronts/2-css/1.códigos/8.animations/1.transitions/3.transition-timing-function.md",
    "2.fronts/2-css/1.códigos/8.animations/1.transitions/2.transition-duration.md",
    "2.fronts/2-css/1.códigos/8.animations/1.transitions/1.transition-property.md",
    "2.fronts/2-css/1.códigos/8.animations/1.transitions/0.Transition O que é.md",
    "2.fronts/2-css/1.códigos/8.animations/1.transitions/5.transition.md",
    "2.fronts/2-css/1.códigos/8.animations/1.transitions/1.PTTA.md",
    "2.fronts/2-css/1.códigos/8.animations/1.transitions/2.explicação.md",
    "2.fronts/2-css/1.códigos/7.overflow/1.Overflow.md",
    "2.fronts/2-css/1.códigos/6.pseudo class e elementos e seletores compostos/3.pseudo classe/7.not().md",
    "2.fronts/2-css/1.códigos/5.display/5.Flex/0.flex/1.FLEXBOX.md",
    "2.fronts/2-css/1.códigos/8.animations/3.opacity/1.opacity.md",
    "2.fronts/2-css/1.códigos/8.animations/2.transformes/4.scale/1.scale.md",
    "2.fronts/2-css/1.códigos/8.animations/2.transformes/5.skew/1.skew.md",
    "2.fronts/2-css/1.códigos/8.animations/2.transformes/3.rotate/1.rotate.md",
    "2.fronts/2-css/1.códigos/8.animations/2.transformes/2.transform-origin/1.transform-origin.md",
    "2.fronts/2-css/1.códigos/8.animations/2.transformes/1.translate/1.translate.md",
    "2.fronts/2-css/1.códigos/8.animations/2.transformes/2.transform-origin",
    "2.fronts/2-css/1.códigos/8.animations/1.transformes/4",
    "2.fronts/2-css/1.códigos/8.animations/2.transformes/0.O que é transform/0.O que é.md",
    "2.fronts/2-css/1.códigos/7.overflow/6. x e y.md",
    "2.fronts/2-css/1.códigos/6.pseudo class e elementos e seletores compostos/5.identificadores familiar/3.filhos posteriores.md",
    "2.fronts/2-css/1.códigos/8.animations/2.transformes/5.skew",
    "2.fronts/2-css/1.códigos/8.animations/2.transformes/4.scale",
    "2.fronts/2-css/1.códigos/8.animations/2.transformes/3.rotate",
    "2.fronts/2-css/1.códigos/8.animations/2.transformes/0.O que é transform",
    "2.fronts/2-css/1.códigos/8.animations/2.transformes/1.translate",
    "2.fronts/2-css/1.códigos/7.overflow/5.scroll.md",
    "2.fronts/2-css/1.códigos/7.overflow/4.auto.md",
    "2.fronts/2-css/1.códigos/7.overflow/3.hiden.md",
    "2.fronts/2-css/1.códigos/7.overflow/2.visible.md",
    "2.fronts/2-css/1.códigos/7.overflow/2.webkit-scrollbar.md",
    "2.fronts/2-css/1.códigos/6.pseudo class e elementos e seletores compostos/5.identificadores familiar/4.descendente.md",
    "2.fronts/2-css/1.códigos/6.pseudo class e elementos e seletores compostos/6.indentificador por atributo",
    "2.fronts/2-css/1.códigos/6.pseudo class e elementos e seletores compostos/3.pseudo classe/Sem título",
    "2.fronts/2-css/1.códigos/6.pseudo class e elementos e seletores compostos/1.id"
  ]
}